fastapi_bgtasks_dashboard/__init__.py
fastapi_bgtasks_dashboard/core.py
fastapi_bgtasks_dashboard/dashboard.py
fastapi_bgtasks_dashboard/route.py
fastapi_bgtasks_dashboard/utils.py
fastapi_bgtasks_dashboard-0.1.5.dist-info/licenses/LICENSE
fastapi_bgtasks_dashboard-0.1.5.dist-info/METADATA
fastapi_bgtasks_dashboard-0.1.5.dist-info/WHEEL
fastapi_bgtasks_dashboard-0.1.5.dist-info/top_level.txt
fastapi_bgtasks_dashboard-0.1.5.dist-info/RECORD
