Metadata-Version: 2.4
Name: fastapi-bgtasks-dashboard
Version: 0.1.5
Summary: Lightweight background task dashboard with FastAPI BackgroundTasks
Author-email: Harshil Jani <harshiljani2002@gmail.com>
Project-URL: Homepage, https://github.com/Harshil-Jani/fastapi-bgtasks-dashboard
Project-URL: Repository, https://github.com/Harshil-Jani/fastapi-bgtasks-dashboard
Requires-Python: >=3.10
License-File: LICENSE
Requires-Dist: fastapi>=0.100.0
Requires-Dist: uvicorn[standard]>=0.23.0
Requires-Dist: pydantic>=2.0
Dynamic: license-file
